Workbook

Sheet Assumptions
A1: Key | B1: Параметр | C1: Значение | D1: Ед. | E1: Источник/уверенность
A2: price_personal | B2: Цена Personal | C2: 7 | D2: €/мес | E2: допущение — середина 6–8
A3: price_family | B3: Цена Family | C3: 13 | D3: €/мес | E3: допущение
A4: free_to_paid | B4: Конверсия Free→Paid | C4: 0.04 | D4: доля | E4: допущение (индустрия 2–5%)
A5: paid_mix_personal | B5: Доля Personal среди платных | C5: 0.7 | D5: доля | E5: допущение
A6: monthly_churn | B6: Месячный churn платных | C6: 0.03 | D6: доля | E6: допущение
A7: ocr_docs_paid | B7: OCR-док/платный/мес | C7: 40 | D7: шт | E7: допущение
A8: ai_q_paid | B8: AI-вопросов/платный/мес | C8: 120 | D8: шт | E8: допущение
A9: storage_paid_gb | B9: Хранилище/платный | C9: 5 | D9: ГБ | E9: допущение
A10: ocr_cost_doc | B10: Себестоимость OCR/док | C10: 0.004 | D10: € | E10: Tesseract self-host: CPU-время
A11: ai_cost_q | B11: Себестоимость AI/вопрос | C11: 0.02 | D11: € | E11: допущение по токенам+embeddings
A12: storage_cost_gb | B12: Хранилище | C12: 0.023 | D12: €/ГБ/мес | E12: класс S3-совместимого хранения
A13: infra_fixed | B13: Фиксированная инфра/мес | C13: 60 | D13: € | E13: VPS+бэкапы+мониторинг (funti.cc-класс)
... A16: free_active | B16: Активных Free (сценарий) | C16: 1000 | D16: чел | E16: вход сценария

Sheet Infrastructure Costs
A1: Статья | B1: Формула | C1: €/мес
A2: Фиксированная инфраструктура | B2: =infra_fixed -> 60 | C2: =Assumptions!$C$13 -> 60
A3: Примечание | B3: Масштабируется ступенчато, не линейно | C3: —

Sheet AI Costs
A1: Показатель | B1: Формула | C1: Значение
A2: AI-вопросов на платного/мес | B2: =Assumptions!$C$8 -> 120 | C2: =Assumptions!$C$8 -> 120
A3: Себестоимость AI/вопрос (€) | B3: =Assumptions!$C$11 -> 0.02 | C3: =Assumptions!$C$11 -> 0.02
A4: AI-затраты на платного/мес (€) | B4: ai_q_paid*ai_cost_q | C4: =Assumptions!$C$8*Assumptions!$C$11 -> 2.4

Sheet OCR Costs
A1: Показатель | B1: Формула | C1: Значение
A2: OCR-док на платного/мес | B2: =Assumptions!$C$7 -> 40 | C2: =Assumptions!$C$7 -> 40
A3: Себестоимость OCR/док (€) | B3: =Assumptions!$C$10 -> 0.004 | C3: =Assumptions!$C$10 -> 0.004
A4: OCR-затраты на платного/мес (€) | B4: ocr_docs_paid*ocr_cost_doc | C4: =Assumptions!$C$7*Assumptions!$C$10 -> 0.16

Sheet Storage Costs
A1: Показатель | B1: Формула | C1: Значение
A2: Хранилище на платного (ГБ) | B2: =Assumptions!$C$9 -> 5 | C2: =Assumptions!$C$9 -> 5
A3: Стоимость хранения (€/ГБ/мес) | B3: =Assumptions!$C$12 -> 0.023 | C3: =Assumptions!$C$12 -> 0.023
A4: Storage-затраты на платного/мес (€) | B4: storage_paid_gb*storage_cost_gb | C4: =Assumptions!$C$9*Assumptions!$C$12 -> 0.115

Sheet Per User Costs
A1: Показатель | B1: Формула | C1: €/мес
A2: AI на платного | B2: 'AI Costs'!C4 | C2: ='AI Costs'!C4 -> 2.4
A3: OCR на платного | B3: 'OCR Costs'!C4 | C3: ='OCR Costs'!C4 -> 0.16
A4: Storage на платного | B4: 'Storage Costs'!C4 | C4: ='Storage Costs'!C4 -> 0.115
A5: Переменная себестоимость платного (COGS) | B5: сумма выше | C5: =C2+C3+C4 -> 2.675
A6: Средняя цена платного (blended) | B6: personal*mix+family*(1-mix) | C6: =Assumptions!$C$2*Assumptions!$C$5+Assumptions!$C$3*(1-Assumptions!$C$5) -> 8.8
A7: Комиссия платежа (€) | B7: price*pct+fixed | C7: =C6*Assumptions!$C$14+Assumptions!$C$15 -> 0.5052
A8: Маржинальная прибыль с платного (€) | B8: цена - COGS - комиссия | C8: =C6-C5-C7 -> 5.6198
A9: Валовая маржа платного (%) | B9: прибыль/цена | C9: =C8/C6 -> 0.63861364

Sheet Scenario Analysis
A1: Сценарий (Free MAU) | B1: Платных | C1: Выручка/мес € | D1: COGS/мес € | E1: Инфра € | F1: Прибыль/мес €
A2: Малый | B2: =ROUND(1000*Assumptions!$C$4,0) -> 40 | C2: =B2*'Per User Costs'!C6 -> 352 | D2: =B2*'Per User Costs'!C5 -> 107 | E2: ='Infrastructure Costs'!C2*MAX(1,ROUNDUP(B2/500,0)) -> 60 | F2: =C2-D2-E2 -> 185
A3: Средний | B3: =ROUND(10000*Assumptions!$C$4,0) -> 400 | C3: =B3*'Per User Costs'!C6 -> 3520 | D3: =B3*'Per User Costs'!C5 -> 1070 | E3: ='Infrastructure Costs'!C2*MAX(1,ROUNDUP(B3/500,0)) -> 60 | F3: =C3-D3-E3 -> 2390
A4: Крупный | B4: =ROUND(100000*Assumptions!$C$4,0) -> 4000 | C4: =B4*'Per User Costs'!C6 -> 35200 | D4: =B4*'Per User Costs'!C5 -> 10700 | E4: ='Infrastructure Costs'!C2*MAX(1,ROUNDUP(B4/500,0)) -> 480 | F4: =C4-D4-E4 -> 24020

Sheet Break-even
A1: Показатель | B1: Формула | C1: Значение
A2: Маржинальная прибыль с платного (€) | B2: Per User Costs!C8 | C2: ='Per User Costs'!C8 -> 5.6198
A3: Фикс. инфра базовая (€/мес) | B3: Infrastructure Costs!C2 | C3: ='Infrastructure Costs'!C2 -> 60
A4: Платных для покрытия базовой инфры | B4: infra/маржа | C4: =ROUNDUP(C3/C2,0) -> 11
A5: Free для этого (при конверсии) | B5: платные/конверсия | C5: =ROUNDUP(C4/Assumptions!$C$4,0) -> 275
A6: LTV платного (€) | B6: маржа/churn | C6: =C2/Assumptions!$C$6 -> 187.32667
